{
  "project_info": {
    "project_number": "373795688682",
    "project_id": "emergencyassistant-c8a46",
    "storage_bucket": "emergencyassistant-c8a46.firebasestorage.app"
  },
  "client": [
    {
      "client_info": {
        "mobilesdk_app_id": "1:373795688682:android:57d8be24a0a3452eaa4793",
        "android_client_info": {
          "package_name": "com.example.emergency_app"
        }
      },
      "oauth_client": [],
      "api_key": [
        {
          "current_key": "AIzaSyBKcGDEvX-UsC68YgblVQC0pIx3-j6by40"
        }
      ],
      "services": {
        "appinvite_service": {
          "other_platform_oauth_client": []
        }
      }
    }
  ],
  "configuration_version": "1"
}